flaskoidc/__init__.py
flaskoidc/config.py
flaskoidc/store.py
tzflaskoidc-6.6.8.dist-info/LICENSE
tzflaskoidc-6.6.8.dist-info/METADATA
tzflaskoidc-6.6.8.dist-info/WHEEL
tzflaskoidc-6.6.8.dist-info/top_level.txt
tzflaskoidc-6.6.8.dist-info/RECORD
