Metadata-Version: 2.1
Name: tzflaskoidc
Version: 6.6.8
Summary: Flask wrapper with pre-configured OIDC support
Home-page: https://github.com/verdan/flaskoidc.git
Author: Verdan Mahmood
Author-email: verdan.mahmood@gmail.com
License: UNKNOWN
Platform: UNKNOWN
Requires-Python: >=3.6
Requires-Dist: Flask (==1.0.2)
Requires-Dist: tz-flask-oidc (==1.4.0)
Requires-Dist: Flask-Session (==0.3.2)
Requires-Dist: Flask-SQLAlchemy (==2.4.4)
